replcraft/__init__.py
replcraft/jarci.py
replcraft/jarci2.py
replcraft_jarci-1.5.1.3.dist-info/LICENSE
replcraft_jarci-1.5.1.3.dist-info/METADATA
replcraft_jarci-1.5.1.3.dist-info/WHEEL
replcraft_jarci-1.5.1.3.dist-info/top_level.txt
replcraft_jarci-1.5.1.3.dist-info/RECORD
