Metadata-Version: 2.1
Name: replcraft-jarci
Version: 1.5.1.3
Summary: Implementation of Replcraft in Python
Home-page: https://github.com/techpixel/replcraft-jarci
Author: techpixel
Author-email: yralqfwus@mozmail.com
Project-URL: Bug Tracker, https://github.com/techpixel/replcraft-jarci/issues
Classifier: Programming Language :: Python :: 3
Classifier: License :: OSI Approved :: MIT License
Classifier: Operating System :: OS Independent
Requires-Python: >=3.6
License-File: LICENSE
